pycoyote/__init__.py
pycoyote/component.py
pycoyote-0.0.8.dist-info/METADATA
pycoyote-0.0.8.dist-info/WHEEL
pycoyote-0.0.8.dist-info/top_level.txt
pycoyote-0.0.8.dist-info/RECORD
