Metadata-Version: 2.1
Name: pycoyote
Version: 0.0.8
Summary: A Python library for building Web user interfaces
Home-page: https://github.com/stonezhong/pycoyote
Author: Stone Zhong
Author-email: stonezhong@hotmail.com
License: MIT
Classifier: License :: OSI Approved :: MIT License
Classifier: Programming Language :: Python :: 3
